vtfree/__init__.py
vtfree/client.py
vtfree/contrib.py
vtfree/exceptions.py
vtfree/log.py
vtfree/utils.py
vtfree-0.1.1.dist-info/METADATA
vtfree-0.1.1.dist-info/WHEEL
vtfree-0.1.1.dist-info/top_level.txt
vtfree-0.1.1.dist-info/RECORD
