Metadata-Version: 2.4
Name: vtfree
Version: 0.1.1
Summary: Polite VirusTotal Public API v3 client
Author-email: nand0san <hancaidolosdos@hotmail.com>
License: MIT
Project-URL: Homepage, https://github.com/nand0san/vtfree
Project-URL: Issues, https://github.com/nand0san/vtfree/issues
Requires-Python: >=3.9
Requires-Dist: requests>=2.31
Requires-Dist: python-dotenv>=1.0
